siminotes/__init__.py
siminotes/__main__.py
siminotes/collect_files.py
siminotes/embedding.py
siminotes/utils.py
siminotes-0.1.1.dist-info/LICENSE.md
siminotes-0.1.1.dist-info/METADATA
siminotes-0.1.1.dist-info/WHEEL
siminotes-0.1.1.dist-info/entry_points.txt
siminotes-0.1.1.dist-info/top_level.txt
siminotes-0.1.1.dist-info/RECORD
