Metadata-Version: 2.1
Name: siminotes
Version: 0.1.1
Summary: A CLI tool for discovering similar notes within your note collection.
Author-email: Roopkumar Das <roopkumards@gmail.com>
License: MIT License
Project-URL: Homepage, https://github.com/RoopkumarD/similar_notes
Project-URL: Repository, https://github.com/RoopkumarD/similar_notes
Project-URL: Issues, https://github.com/RoopkumarD/similar_notes/issues
Keywords: Vector embeddings,similarity,CLI,notes,finder,search,tool,text analysis
License-File: LICENSE.md
Requires-Dist: sentence-transformers >=2.2.2
